setup.py
gowalla/__init__.py
gowalla/gowalla.py
gowalla.egg-info/PKG-INFO
gowalla.egg-info/SOURCES.txt
gowalla.egg-info/dependency_links.txt
gowalla.egg-info/top_level.txt