Metadata-Version: 1.1
Name: gowalla
Version: 1.0
Summary: Gowalla API wrapper
Home-page: http://github.com/sentineldesign/python-gowalla/
Author: Drew Yeaton
Author-email: drew@sentineldesign.net
License: GPLv3
Download-URL: http://pypi.python.org/pypi/gowalla/
Keywords: gowalla rest simplejson wrapper social location
Platform: Platform Independent
Classifier: Development Status :: 5 - Production/Stable
Classifier: Intended Audience :: Developers
Classifier: License :: OSI Approved :: GNU General Public License (GPL)
Classifier: Natural Language :: English
Classifier: Operating System :: OS Independent
Classifier: Programming Language :: Python
Classifier: Topic :: Software Development :: Libraries :: Python Modules
Requires: simplejson
